LICENSE
MANIFEST.in
README.md
setup.py
testingintegrationsplan2pointopointo/__init__.py
testingintegrationsplan2pointopointo/api_helper.py
testingintegrationsplan2pointopointo/configuration.py
testingintegrationsplan2pointopointo/decorators.py
testingintegrationsplan2pointopointo/testingintegrationsplan_2_pointopointo_client.py
testingintegrationsplan2pointopointo.egg-info/PKG-INFO
testingintegrationsplan2pointopointo.egg-info/SOURCES.txt
testingintegrationsplan2pointopointo.egg-info/dependency_links.txt
testingintegrationsplan2pointopointo.egg-info/requires.txt
testingintegrationsplan2pointopointo.egg-info/top_level.txt
testingintegrationsplan2pointopointo/controllers/__init__.py
testingintegrationsplan2pointopointo/controllers/base_controller.py
testingintegrationsplan2pointopointo/controllers/pet_controller.py
testingintegrationsplan2pointopointo/controllers/store_controller.py
testingintegrationsplan2pointopointo/controllers/user_controller.py
testingintegrationsplan2pointopointo/exceptions/__init__.py
testingintegrationsplan2pointopointo/exceptions/api_exception.py
testingintegrationsplan2pointopointo/http/__init__.py
testingintegrationsplan2pointopointo/http/http_call_back.py
testingintegrationsplan2pointopointo/http/http_client.py
testingintegrationsplan2pointopointo/http/http_context.py
testingintegrationsplan2pointopointo/http/http_method_enum.py
testingintegrationsplan2pointopointo/http/http_request.py
testingintegrationsplan2pointopointo/http/http_response.py
testingintegrationsplan2pointopointo/http/requests_client.py
testingintegrationsplan2pointopointo/models/__init__.py
testingintegrationsplan2pointopointo/models/api_response.py
testingintegrationsplan2pointopointo/models/category.py
testingintegrationsplan2pointopointo/models/o_auth_scope_enum.py
testingintegrationsplan2pointopointo/models/order.py
testingintegrationsplan2pointopointo/models/pet.py
testingintegrationsplan2pointopointo/models/status_1_enum.py
testingintegrationsplan2pointopointo/models/status_2_enum.py
testingintegrationsplan2pointopointo/models/status_enum.py
testingintegrationsplan2pointopointo/models/tag.py
testingintegrationsplan2pointopointo/models/user.py